QUANTAXIS/__init__.py
QUANTAXIS/__main__.py
QUANTAXIS/QAARP/QAAccount.c
QUANTAXIS/QAARP/QAAccount.py
QUANTAXIS/QAARP/QAAccount.pyx
QUANTAXIS/QAARP/QAAccountPro.py
QUANTAXIS/QAARP/QAPortfolio.py
QUANTAXIS/QAARP/QARisk.py
QUANTAXIS/QAARP/QAStrategy.py
QUANTAXIS/QAARP/QAUser.py
QUANTAXIS/QAARP/__init__.py
QUANTAXIS/QAARP/abount_account.md
QUANTAXIS/QAARP/market_preset.py
QUANTAXIS/QAARP/readme.md
QUANTAXIS/QAAnalysis/QAAnalysis_account.py
QUANTAXIS/QAAnalysis/QAAnalysis_block.py
QUANTAXIS/QAAnalysis/QAAnalysis_dataframe.py
QUANTAXIS/QAAnalysis/QAAnalysis_machinelearning.py
QUANTAXIS/QAAnalysis/QAAnalysis_series.py
QUANTAXIS/QAAnalysis/QAAnalysis_signal.py
QUANTAXIS/QAAnalysis/QAAnalysis_tick.py
QUANTAXIS/QAAnalysis/QAAnalysis_trade.py
QUANTAXIS/QAAnalysis/__init__.py
QUANTAXIS/QAApplication/OldBacktest.py
QUANTAXIS/QAApplication/QAAnalysis.py
QUANTAXIS/QAApplication/QABacktest.py
QUANTAXIS/QAApplication/QAResult.py
QUANTAXIS/QAApplication/QAT0Backtest.py
QUANTAXIS/QAApplication/QATradeRealtime.py
QUANTAXIS/QAApplication/__init__.py
QUANTAXIS/QAApplication/backtest_setting.py
QUANTAXIS/QACmd/__init__.py
QUANTAXIS/QACmd/runner.py
QUANTAXIS/QAData/QABlockStruct.py
QUANTAXIS/QAData/QADataStruct.py
QUANTAXIS/QAData/QAFinancialStruct.py
QUANTAXIS/QAData/QAIndicatorStruct.py
QUANTAXIS/QAData/QASeriesStruct.py
QUANTAXIS/QAData/__init__.py
QUANTAXIS/QAData/base_datastruct.py
QUANTAXIS/QAData/data_fq.py
QUANTAXIS/QAData/data_marketvalue.py
QUANTAXIS/QAData/data_resample.py
QUANTAXIS/QAData/dsmethods.py
QUANTAXIS/QAData/financial_mean.py
QUANTAXIS/QAData/readme.md
QUANTAXIS/QAData/realtimedata.py
QUANTAXIS/QAData/serialize.py
QUANTAXIS/QAData/proto/order.proto
QUANTAXIS/QAData/proto/stock_day.proto
QUANTAXIS/QAData/proto/stock_hq.proto
QUANTAXIS/QAData/proto/stock_info.proto
QUANTAXIS/QAData/proto/stock_min.proto
QUANTAXIS/QAData/proto/stock_realtime.proto
QUANTAXIS/QAData/proto/stock_tick.proto
QUANTAXIS/QAEngine/QAAsyncExec.py
QUANTAXIS/QAEngine/QAAsyncSchedule.py
quantaxis-1.10.19.dist-info/LICENSE
quantaxis-1.10.19.dist-info/METADATA
quantaxis-1.10.19.dist-info/WHEEL
quantaxis-1.10.19.dist-info/entry_points.txt
quantaxis-1.10.19.dist-info/top_level.txt
quantaxis-1.10.19.dist-info/zip-safe
quantaxis-1.10.19.dist-info/RECORD
